Iverilog/subtratorcompleto/subtratorcompleto.v
module subtratorcompleto (a, b, cin, s, cout);
    input a, b, cin;
    output s, cout;

    assign s = a ^ b ^ cin;
    assign cout = (~a & b) | (~a & cin) | (b & cin) ;
endmodule

Iverilog/subtratorcompleto/subtratorcompleto_tb.v
`include "subtratorcompleto.v"
`timescale 1ns/100ps

module subtratorcompleto_tb;
    reg a0, b0, cin0;
    wire s0, cout0;
    subtratorcompleto uut (.a(a0),.b(b0),.cin(cin0),.s(s0),.cout(cout0));

    initial begin
        $dumpfile("subtratorcompleto.vcd");
        $dumpvars(0, subtratorcompleto_tb);
        
        a0 = 0; b0 = 0; cin0 = 0;
        #10; a0 = 0; b0 = 0; cin0 = 1;
        #10; a0 = 0; b0 = 1; cin0 = 0;
        #10; a0 = 0; b0 = 1; cin0 = 1;
        #10; a0 = 1; b0 = 0; cin0 = 0;
        #10; a0 = 1; b0 = 0; cin0 = 1;
        #10; a0 = 1; b0 = 1; cin0 = 0;
        #10; a0 = 1; b0 = 1; cin0 = 1;
        #10; $finish;
    end
endmodule

Iverilog/subtratorcompleto/subtratorcompleto.vcd
$date
	Sun Sep 07 23:45:09 2025
$end
$version
	Icarus Verilog
$end
$timescale
	100ps
$end
$scope module subtratorcompleto_tb $end
$var wire 1 ! s0 $end
$var wire 1 " cout0 $end
$var reg 1 # a0 $end
$var reg 1 $ b0 $end
$var reg 1 % cin0 $end
$scope module uut $end
$var wire 1 # a $end
$var wire 1 $ b $end
$var wire 1 % cin $end
$var wire 1 " cout $end
$var wire 1 ! s $end
$upscope $end
$upscope $end
$enddefinitions $end
$comment Show the parameter values. $end
$dumpall
$end
#0
$dumpvars
0%
0$
0#
0"
0!
$end
#100
1"
1!
1%
#200
0%
1$
#300
0!
1%
#400
0"
1!
0%
0$
1#
#500
0!
1%
#600
0%
1$
#700
1"
1!
1%
