VHDL/Projetos_Moore_1001/moore_1001.vhd
-- FSM Moore para detectar sequência "1001"
library ieee;
use ieee.std_logic_1164.all;

entity moore_1001 is
    port (
        clk     : in std_logic;
        reset   : in std_logic;
        din     : in std_logic;
        dout    : out std_logic
    );
end moore_1001;

architecture behavior of moore_1001 is
    type state_type is (S0, S1, S2, S3, S4);
    signal state, next_state : state_type;
begin

    -- Processo de transição de estado com reset síncrono
    process(clk, reset)
    begin
        if reset = '1' then
            state <= S0;
        elsif rising_edge(clk) then
            state <= next_state;
        end if;
    end process;

    -- Processo de lógica de transição e definição da saída Moore
    process(state, din)
    begin
        case state is
            when S0 =>
                dout <= '0';
                if din = '1' then
                    next_state <= S1;
                else
                    next_state <= S0;
                end if;

            when S1 =>
                dout <= '0';
                if din = '0' then
                    next_state <= S2;
                else
                    next_state <= S1;
                end if;

            when S2 =>
                dout <= '0';
                if din = '0' then
                    next_state <= S3; -- ← CORRIGIDO
                else
                    next_state <= S1;
                end if;

            when S3 =>
                dout <= '0';
                if din = '1' then
                    next_state <= S4; -- sequência "1001" completa
                else
                    next_state <= S0;
                end if;

            when S4 =>
                dout <= '1'; -- ← saída Moore ativada no estado
                if din = '1' then
                    next_state <= S1;
                else
                    next_state <= S0;
                end if;

            when others =>
                dout <= '0';
                next_state <= S0;
        end case;
    end process;

end behavior;

VHDL/Projetos_Moore_1001/tb_moore_1001.vhd
library ieee;
use ieee.std_logic_1164.all;

entity tb_moore_1001 is
end tb_moore_1001;

architecture test of tb_moore_1001 is
    signal clk   : std_logic := '0';
    signal reset : std_logic := '1';
    signal din   : std_logic := '0';
    signal dout  : std_logic;

    component moore_1001
        port (
            clk   : in std_logic;
            reset : in std_logic;
            din   : in std_logic;
            dout  : out std_logic
        );
    end component;

begin

    -- Instanciação do DUT (Device Under Test)
    uut: moore_1001 port map(clk, reset, din, dout);

    -- Geração de clock (20 ns período)
    clk_process : process
    begin
        while True loop
            clk <= '0'; wait for 10 ns;
            clk <= '1'; wait for 10 ns;
        end loop;
    end process;

    -- Estímulos de entrada
    stim_proc: process
    begin
        -- Reset
        reset <= '1'; wait for 25 ns;
        reset <= '0'; wait for 20 ns;

        -- Sequência correta: "1 0 0 1" → dout = '1' no estado final
        din <= '1'; wait for 20 ns;
        din <= '0'; wait for 20 ns;
        din <= '0'; wait for 20 ns;
        din <= '1'; wait for 20 ns;

        -- Espera e aplica nova sequência válida
        wait for 40 ns;
        din <= '1'; wait for 20 ns;
        din <= '0'; wait for 20 ns;
        din <= '0'; wait for 20 ns;
        din <= '1'; wait for 20 ns;

        -- Fim do teste
        wait;
    end process;

end test;

VHDL/Projetos_Moore_1001/moore_1001.vcd
$date
  Thu Aug 07 15:13:37 2025
$end
$version
  GHDL v0
$end
$timescale
  1 fs
$end
$scope module standard $end
$upscope $end
$scope module std_logic_1164 $end
$upscope $end
$scope module tb_moore_1001 $end
$var reg 1 ! clk $end
$var reg 1 " reset $end
$var reg 1 # din $end
$var reg 1 $ dout $end
$scope module uut $end
$var reg 1 % clk $end
$var reg 1 & reset $end
$var reg 1 ' din $end
$var reg 1 ( dout $end
$comment state is not handled $end
$comment next_state is not handled $end
$upscope $end
$upscope $end
$enddefinitions $end
#0
0!
1"
0#
0$
0%
1&
0'
0(
#10000000
1!
1%
#20000000
0!
0%
#25000000
0"
0&
#30000000
1!
1%
#40000000
0!
0%
#45000000
1#
1'
#50000000
1!
1%
#60000000
0!
0%
#65000000
0#
0'
#70000000
1!
1%
#80000000
0!
0%
#85000000
#90000000
1!
1%
#100000000
0!
0%
#105000000
1#
1'
#110000000
1!
1$
1%
1(
#120000000
0!
0%
#125000000
#130000000
1!
0$
1%
0(
#140000000
0!
0%
#150000000
1!
1%
#160000000
0!
0%
#165000000
#170000000
1!
1%
#180000000
0!
0%
#185000000
0#
0'
#190000000
1!
1%
#200000000
0!
0%
#205000000
#210000000
1!
1%
#220000000
0!
0%
#225000000
1#
1'
#230000000
1!
1$
1%
1(
#240000000
0!
0%
#245000000
#250000000
1!
0$
1%
0(
