Iverilog/codificadorbcd3x2/codificadorbcd3x2.v
module codificadorbcd3x2(e1, e2, e3, s0, s1);
    input e1, e2, e3;
    output s0, s1;

assign s0 = e2 | e3;
assign s1 = e1 | e3;
endmodule

Iverilog/codificadorbcd3x2/codificadorbcd3x2_tb.v
`include "codificadorbcd3x2.v"
`timescale 1ns/100ps

module codificadorbcd3x2_tb;
reg e1, e2, e3;
wire s0, s1;
codificadorbcd3x2 uut (.e1(e1),.e2(e2),.e3(e3),.s0(s0),.s1(s1));

initial begin
$dumpfile("codificadorbcd3x2.vcd");
$dumpvars(0, codificadorbcd3x2_tb);
     e1 = 0; e2 = 0; e3 = 0;
#10; e1 = 0; e2 = 0; e3 = 1; 
#10; e1 = 0; e2 = 1; e3 = 0; 
#10; e1 = 0; e2 = 1; e3 = 1; 
#10; e1 = 1; e2 = 0; e3 = 0; 
#10; e1 = 1; e2 = 0; e3 = 1;
#10; e1 = 1; e2 = 1; e3 = 0; 
#10; e1 = 1; e2 = 1; e3 = 1; 
#10; $finish;
end
endmodule

Iverilog/codificadorbcd3x2/codificadorbcd3x2.vcd
$date
	Thu Aug 21 09:13:40 2025
$end
$version
	Icarus Verilog
$end
$timescale
	100ps
$end
$scope module codificadorbcd3x2_tb $end
$var wire 1 ! s1 $end
$var wire 1 " s0 $end
$var reg 1 # e1 $end
$var reg 1 $ e2 $end
$var reg 1 % e3 $end
$scope module uut $end
$var wire 1 # e1 $end
$var wire 1 $ e2 $end
$var wire 1 % e3 $end
$var wire 1 " s0 $end
$var wire 1 ! s1 $end
$upscope $end
$upscope $end
$enddefinitions $end
$comment Show the parameter values. $end
$dumpall
$end
#0
$dumpvars
0%
0$
0#
0"
0!
$end
#100
1"
1!
1%
#200
0!
0%
1$
#300
1!
1%
#400
0"
0%
0$
1#
#500
1"
1%
#600
0%
1$
#700
1%
