Iverilog/mux4x1/mux4.v
// =============================================
// Módulo: Multiplexador 4 para 1
// =============================================
// Entradas:
//   - I1, I2, I3, I4: dados de entrada
//   - S1, S2: linhas de seleção
// Saída:
//   - O: saída selecionada
// =============================================

module mux4 (
    input wire I1,
    input wire I2,
    input wire I3,
    input wire I4,
    input wire S1,
    input wire S2,
    output wire O
);

    // Seleção usando atribuição condicional
    assign O = (S1 == 0 && S2 == 0) ? I1 :
               (S1 == 0 && S2 == 1) ? I2 :
               (S1 == 1 && S2 == 0) ? I3 :
               I4;

endmodule

Iverilog/mux4x1/mux4_tb.v
// =============================================
// Testbench para o módulo mux4
// =============================================

`include "mux4.v"
`timescale 1ns/1ps

module mux4_tb;

    // Entradas do multiplexador
    reg I1, I2, I3, I4;
    reg S1, S2;
    wire O;

    // Instanciação do DUT (Device Under Test)
    mux4 dut (
        .I1(I1),
        .I2(I2),
        .I3(I3),
        .I4(I4),
        .S1(S1),
        .S2(S2),
        .O(O)
    );

    // Geração das formas de onda
    initial begin
        $dumpfile("mux4.vcd");
        $dumpvars(0, mux4_tb);

        // Teste com diferentes combinações de seleção
        I1 = 0; I2 = 1; I3 = 0; I4 = 1;

        S1 = 0; S2 = 0; #10; // Espera-se O = I1
        S1 = 0; S2 = 1; #10; // Espera-se O = I2
        S1 = 1; S2 = 0; #10; // Espera-se O = I3
        S1 = 1; S2 = 1; #10; // Espera-se O = I4

        // Mudança nas entradas
        I1 = 1; I2 = 0; I3 = 1; I4 = 0;

        S1 = 0; S2 = 0; #10; // Espera-se O = I1
        S1 = 0; S2 = 1; #10; // Espera-se O = I2
        S1 = 1; S2 = 0; #10; // Espera-se O = I3
        S1 = 1; S2 = 1; #10; // Espera-se O = I4

        $finish;
    end

endmodule

Iverilog/mux4x1/mux4.vcd
$date
	Thu Aug 21 11:21:35 2025
$end
$version
	Icarus Verilog
$end
$timescale
	1ps
$end
$scope module mux4_tb $end
$var wire 1 ! O $end
$var reg 1 " I1 $end
$var reg 1 # I2 $end
$var reg 1 $ I3 $end
$var reg 1 % I4 $end
$var reg 1 & S1 $end
$var reg 1 ' S2 $end
$scope module dut $end
$var wire 1 " I1 $end
$var wire 1 # I2 $end
$var wire 1 $ I3 $end
$var wire 1 % I4 $end
$var wire 1 & S1 $end
$var wire 1 ' S2 $end
$var wire 1 ! O $end
$upscope $end
$upscope $end
$enddefinitions $end
$comment Show the parameter values. $end
$dumpall
$end
#0
$dumpvars
0'
0&
1%
0$
1#
0"
0!
$end
#10000
1!
1'
#20000
0!
0'
1&
#30000
1!
1'
#40000
0'
0&
0%
1$
0#
1"
#50000
0!
1'
#60000
1!
0'
1&
#70000
0!
1'
