Iverilog/paridade_impar/paridade_impar.v
module paridade_impar (a, b, c, s);
input a, b, c;
output s;

assign s = a ^ b ^ c;
endmodule

Iverilog/paridade_impar/paridade_impar_tb.v
`include "paridade_impar.v"
`timescale 1ns/100ps

module paridade_impar_tb;
reg a0, b0, c0;
wire s0;
paridade_impar uut (.a(a0),.b(b0),.c(c0),.s(s0));

initial begin
$dumpfile("paridade_impar.vcd");
$dumpvars(0, paridade_impar_tb);
     a0 = 0; b0 = 0; c0 = 0;
#10; a0 = 0; b0 = 0; c0 = 1; 
#10; a0 = 0; b0 = 1; c0 = 0; 
#10; a0 = 0; b0 = 1; c0 = 1; 
#10; a0 = 1; b0 = 0; c0 = 0; 
#10; a0 = 1; b0 = 0; c0 = 1;
#10; a0 = 1; b0 = 1; c0 = 0; 
#10; a0 = 1; b0 = 1; c0 = 1; 
#10; $finish;
end
endmodule

Iverilog/paridade_impar/paridade_impar.vcd
$date
	Tue Aug 19 11:40:11 2025
$end
$version
	Icarus Verilog
$end
$timescale
	100ps
$end
$scope module paridade_impar_tb $end
$var wire 1 ! s0 $end
$var reg 1 " a0 $end
$var reg 1 # b0 $end
$var reg 1 $ c0 $end
$scope module uut $end
$var wire 1 " a $end
$var wire 1 # b $end
$var wire 1 $ c $end
$var wire 1 ! s $end
$upscope $end
$upscope $end
$enddefinitions $end
$comment Show the parameter values. $end
$dumpall
$end
#0
$dumpvars
0$
0#
0"
0!
$end
#100
1!
1$
#200
0$
1#
#300
0!
1$
#400
1!
0$
0#
1"
#500
0!
1$
#600
0$
1#
#700
1!
1$
