Iverilog/somadorcompleto/somadorcompleto.v
module somadorcompleto (a, b, cin, s, cout);
input a, b, cin;
output s, cout;

assign s = a ^ b ^ cin;
assign cout = (a & b) | (a & cin) | (b & cin);
endmodule

Iverilog/somadorcompleto/somadorcompleto_tb.v
`include "somadorcompleto.v"
`timescale 1ns/100ps

module somadorcompleto_tb;
reg a0, b0, cin0;
wire s0, cout0;
somadorcompleto uut (.a(a0),.b(b0),.cin(cin0),.s(s0),.cout(cout0));

initial begin
$dumpfile("somadorcompleto.vcd");
$dumpvars(0, somadorcompleto_tb);
     a0 = 0; b0 = 0; cin0 = 0;
#10; a0 = 0; b0 = 0; cin0 = 1; 
#10; a0 = 0; b0 = 1; cin0 = 0; 
#10; a0 = 0; b0 = 1; cin0 = 1; 
#10; a0 = 1; b0 = 0; cin0 = 0; 
#10; a0 = 1; b0 = 0; cin0 = 1;
#10; a0 = 1; b0 = 1; cin0 = 0; 
#10; a0 = 1; b0 = 1; cin0 = 1; 
#10; $finish;
end
endmodule

Iverilog/somadorcompleto/somadorcompleto.vcd
$date
	Tue Aug 19 10:37:18 2025
$end
$version
	Icarus Verilog
$end
$timescale
	100ps
$end
$scope module somadorcompleto_tb $end
$var wire 1 ! s0 $end
$var wire 1 " cout0 $end
$var reg 1 # a0 $end
$var reg 1 $ b0 $end
$var reg 1 % cin0 $end
$scope module uut $end
$var wire 1 # a $end
$var wire 1 $ b $end
$var wire 1 % cin $end
$var wire 1 " cout $end
$var wire 1 ! s $end
$upscope $end
$upscope $end
$enddefinitions $end
$comment Show the parameter values. $end
$dumpall
$end
#0
$dumpvars
0%
0$
0#
0"
0!
$end
#100
1!
1%
#200
0%
1$
#300
1"
0!
1%
#400
0"
1!
0%
0$
1#
#500
1"
0!
1%
#600
0%
1$
#700
1!
1%
